[
  {
    "report_id": "r20260622",
    "report_date": "2026-06-22",
    "report_title": "Daily Brief 22 Jun 2026",
    "delivery_channel": "telegram",
    "delivery_status": "sent",
    "sent_at": "2026-06-22T06:57:18.090085+00:00",
    "item_count": 6,
    "confidentiality_level": "internal"
  },
  {
    "report_id": "r20260623",
    "report_date": "2026-06-23",
    "report_title": "Daily Brief 23 Jun 2026",
    "delivery_channel": "telegram",
    "delivery_status": "failed",
    "sent_at": "2026-06-23T05:12:25.302254+00:00",
    "item_count": 11,
    "confidentiality_level": "internal"
  },
  {
    "report_id": "r20260624",
    "report_date": "2026-06-24",
    "report_title": "Daily Brief 24 Jun 2026",
    "delivery_channel": "telegram",
    "delivery_status": "sent",
    "sent_at": "2026-06-24T04:25:35.422952+00:00",
    "item_count": 13,
    "confidentiality_level": "internal"
  },
  {
    "report_id": "r20260625",
    "report_date": "2026-06-25",
    "report_title": "Daily Brief 25 Jun 2026",
    "delivery_channel": "telegram",
    "delivery_status": "sent",
    "sent_at": "2026-06-25T11:21:59.601667+00:00",
    "item_count": 35,
    "confidentiality_level": "internal"
  },
  {
    "report_id": "r20260626",
    "report_date": "2026-06-26",
    "report_title": "Daily Brief 26 Jun 2026",
    "delivery_channel": "telegram",
    "delivery_status": "sent",
    "sent_at": "2026-06-26T01:03:49.946435+00:00",
    "item_count": 12,
    "confidentiality_level": "internal"
  },
  {
    "report_id": "r20260627",
    "report_date": "2026-06-27",
    "report_title": "Daily Brief 27 Jun 2026",
    "delivery_channel": "telegram",
    "delivery_status": "sent",
    "sent_at": "2026-06-27T01:06:37.527788+00:00",
    "item_count": 23,
    "confidentiality_level": "internal"
  },
  {
    "report_id": "r20260628",
    "report_date": "2026-06-28",
    "report_title": "Daily Brief 28 Jun 2026",
    "delivery_channel": "telegram",
    "delivery_status": "failed",
    "sent_at": "2026-06-28T08:37:08.486094+00:00",
    "item_count": 9,
    "confidentiality_level": "internal"
  },
  {
    "report_id": "r20260629",
    "report_date": "2026-06-29",
    "report_title": "Daily Brief 29 Jun 2026",
    "delivery_channel": "telegram",
    "delivery_status": "sent",
    "sent_at": "2026-06-29T09:27:00.939998+00:00",
    "item_count": 12,
    "confidentiality_level": "internal"
  },
  {
    "report_id": "r20260630",
    "report_date": "2026-06-30",
    "report_title": "Daily Brief 30 Jun 2026",
    "delivery_channel": "telegram",
    "delivery_status": "sent",
    "sent_at": "2026-06-30T05:00:13.129808+00:00",
    "item_count": 22,
    "confidentiality_level": "internal"
  },
  {
    "report_id": "r20260701",
    "report_date": "2026-07-01",
    "report_title": "Daily Brief 01 Jul 2026",
    "delivery_channel": "telegram",
    "delivery_status": "sent",
    "sent_at": "2026-06-30T22:55:27.831529+00:00",
    "item_count": 28,
    "confidentiality_level": "internal"
  },
  {
    "report_id": "r20260702",
    "report_date": "2026-07-02",
    "report_title": "Daily Brief 02 Jul 2026",
    "delivery_channel": "telegram",
    "delivery_status": "sent",
    "sent_at": "2026-07-01T22:13:31.358723+00:00",
    "item_count": 16,
    "confidentiality_level": "internal"
  },
  {
    "report_id": "r20260703",
    "report_date": "2026-07-03",
    "report_title": "Daily Brief 03 Jul 2026",
    "delivery_channel": "telegram",
    "delivery_status": "sent",
    "sent_at": "2026-07-03T04:07:45.431722+00:00",
    "item_count": 18,
    "confidentiality_level": "internal"
  },
  {
    "report_id": "r20260704",
    "report_date": "2026-07-04",
    "report_title": "Daily Brief 04 Jul 2026",
    "delivery_channel": "telegram",
    "delivery_status": "sent",
    "sent_at": "2026-07-04T09:33:50.184148+00:00",
    "item_count": 21,
    "confidentiality_level": "internal"
  },
  {
    "report_id": "r20260705",
    "report_date": "2026-07-05",
    "report_title": "Daily Brief 05 Jul 2026",
    "delivery_channel": "telegram",
    "delivery_status": "sent",
    "sent_at": "2026-07-05T09:56:15.228374+00:00",
    "item_count": 11,
    "confidentiality_level": "internal"
  },
  {
    "report_id": "r20260706",
    "report_date": "2026-07-06",
    "report_title": "Daily Brief 06 Jul 2026",
    "delivery_channel": "telegram",
    "delivery_status": "sent",
    "sent_at": "2026-07-06T11:47:22.131522+00:00",
    "item_count": 3,
    "confidentiality_level": "internal"
  },
  {
    "report_id": "r20260707",
    "report_date": "2026-07-07",
    "report_title": "Daily Brief 07 Jul 2026",
    "delivery_channel": "telegram",
    "delivery_status": "sent",
    "sent_at": "2026-07-06T23:40:49.445706+00:00",
    "item_count": 26,
    "confidentiality_level": "internal"
  },
  {
    "report_id": "r20260708",
    "report_date": "2026-07-08",
    "report_title": "Daily Brief 08 Jul 2026",
    "delivery_channel": "telegram",
    "delivery_status": "sent",
    "sent_at": "2026-07-08T06:17:10.630078+00:00",
    "item_count": 20,
    "confidentiality_level": "internal"
  },
  {
    "report_id": "r20260709",
    "report_date": "2026-07-09",
    "report_title": "Daily Brief 09 Jul 2026",
    "delivery_channel": "telegram",
    "delivery_status": "sent",
    "sent_at": "2026-07-09T01:16:09.778627+00:00",
    "item_count": 21,
    "confidentiality_level": "internal"
  },
  {
    "report_id": "r20260710",
    "report_date": "2026-07-10",
    "report_title": "Daily Brief 10 Jul 2026",
    "delivery_channel": "telegram",
    "delivery_status": "sent",
    "sent_at": "2026-07-10T01:15:45.104191+00:00",
    "item_count": 19,
    "confidentiality_level": "internal"
  },
  {
    "report_id": "r20260711",
    "report_date": "2026-07-11",
    "report_title": "Daily Brief 11 Jul 2026",
    "delivery_channel": "telegram",
    "delivery_status": "sent",
    "sent_at": "2026-07-11T01:16:02.958413+00:00",
    "item_count": 15,
    "confidentiality_level": "internal"
  },
  {
    "report_id": "r20260712",
    "report_date": "2026-07-12",
    "report_title": "Daily Brief 12 Jul 2026",
    "delivery_channel": "telegram",
    "delivery_status": "failed",
    "sent_at": "2026-07-12T01:17:19.272363+00:00",
    "item_count": 13,
    "confidentiality_level": "internal"
  },
  {
    "report_id": "r20260713",
    "report_date": "2026-07-13",
    "report_title": "Daily Brief 13 Jul 2026",
    "delivery_channel": "telegram",
    "delivery_status": "sent",
    "sent_at": "2026-07-13T01:15:37.384743+00:00",
    "item_count": 12,
    "confidentiality_level": "internal"
  },
  {
    "report_id": "r20260714",
    "report_date": "2026-07-14",
    "report_title": "Daily Brief 14 Jul 2026",
    "delivery_channel": "telegram",
    "delivery_status": "failed",
    "sent_at": "2026-07-14T01:15:49.182246+00:00",
    "item_count": 20,
    "confidentiality_level": "internal"
  },
  {
    "report_id": "r20260715",
    "report_date": "2026-07-15",
    "report_title": "Daily Brief 15 Jul 2026",
    "delivery_channel": "telegram",
    "delivery_status": "sent",
    "sent_at": "2026-07-15T01:15:40.291570+00:00",
    "item_count": 27,
    "confidentiality_level": "internal"
  },
  {
    "report_id": "r20260716",
    "report_date": "2026-07-16",
    "report_title": "Daily Brief 16 Jul 2026",
    "delivery_channel": "telegram",
    "delivery_status": "sent",
    "sent_at": "2026-07-16T01:15:47.786558+00:00",
    "item_count": 25,
    "confidentiality_level": "internal"
  },
  {
    "report_id": "r20260717",
    "report_date": "2026-07-17",
    "report_title": "Daily Brief 17 Jul 2026",
    "delivery_channel": "telegram",
    "delivery_status": "sent",
    "sent_at": "2026-07-17T01:15:47.537534+00:00",
    "item_count": 25,
    "confidentiality_level": "internal"
  },
  {
    "report_id": "r20260718",
    "report_date": "2026-07-18",
    "report_title": "Daily Brief 18 Jul 2026",
    "delivery_channel": "telegram",
    "delivery_status": "sent",
    "sent_at": "2026-07-18T01:15:45.233707+00:00",
    "item_count": 21,
    "confidentiality_level": "internal"
  }
]